cryptoclip.py
cryptoclip-1.1.1.dist-info/DESCRIPTION.rst
cryptoclip-1.1.1.dist-info/METADATA
cryptoclip-1.1.1.dist-info/RECORD
cryptoclip-1.1.1.dist-info/WHEEL
cryptoclip-1.1.1.dist-info/entry_points.txt
cryptoclip-1.1.1.dist-info/metadata.json
cryptoclip-1.1.1.dist-info/top_level.txt
