Metadata-Version: 2.0
Name: cryptoclip
Version: 1.1.1
Summary: Command-line implementation of ComboCrypt for clipboard data
Home-page: https://github.com/samrankin1/cryptoclip
Author: Sam Rankin
Author-email: sam.rankin@me.com
License: MIT
Keywords: encryption public-key rsa aes clipboard
Platform: UNKNOWN
Classifier: Development Status :: 4 - Beta
Classifier: Intended Audience :: End Users/Desktop
Classifier: License :: OSI Approved :: MIT License
Classifier: Natural Language :: English
Classifier: Operating System :: OS Independent
Classifier: Topic :: Utilities
Classifier: Programming Language :: Python :: 3
Classifier: Programming Language :: Python :: 3.3
Classifier: Programming Language :: Python :: 3.4
Classifier: Programming Language :: Python :: 3.5
Requires-Dist: combocrypt (>=2.0.0)
Requires-Dist: pyperclip
